utdquake/__init__.py
utdquake/core/__init__.py
utdquake/core/config.py
utdquake/core/data.py
utdquake/core/load.py
utdquake/core/utdquake.py
utdquake/utils/__init__.py
utdquake/utils/plot.py
utdquake/utils/utils.py
utdquake-0.1.dist-info/licenses/LICENSE
utdquake-0.1.dist-info/METADATA
utdquake-0.1.dist-info/WHEEL
utdquake-0.1.dist-info/top_level.txt
utdquake-0.1.dist-info/RECORD
