Metadata-Version: 2.4
Name: utdquake
Version: 0.1
Summary: University of Texas at Dallas Earthquake Dataset
Home-page: https://github.com/ecastillot/UTDQuake
Author: ecastillot (Emmanuel Castillo)
Author-email: <castillo.280997@gmail.com>
Keywords: python,utdquake,earthquakes,seismology
Classifier: Development Status :: 1 - Planning
Classifier: Intended Audience :: Developers
Classifier: Programming Language :: Python :: 3
Classifier: License :: OSI Approved :: GNU General Public License v3 (GPLv3)
Classifier: Operating System :: Unix
Requires-Python: >=3.10
License-File: LICENSE
Requires-Dist: datasets
Requires-Dist: huggingface-hub
Requires-Dist: obspy
Requires-Dist: obsplus
Requires-Dist: pandas
Requires-Dist: pyarrow
Requires-Dist: numpy
Requires-Dist: matplotlib
Requires-Dist: seaborn
Requires-Dist: packaging
Requires-Dist: scipy
Dynamic: author
Dynamic: author-email
Dynamic: classifier
Dynamic: description
Dynamic: description-content-type
Dynamic: home-page
Dynamic: keywords
Dynamic: license-file
Dynamic: requires-dist
Dynamic: requires-python
Dynamic: summary
